pyrubrum/__init__.py
pyrubrum/database/__init__.py
pyrubrum/database/base_database.py
pyrubrum/database/dict_database.py
pyrubrum/database/redis_database.py
pyrubrum/database/errors/__init__.py
pyrubrum/database/errors/delete_error.py
pyrubrum/database/errors/error.py
pyrubrum/database/errors/expire_error.py
pyrubrum/database/errors/get_error.py
pyrubrum/database/errors/not_found_error.py
pyrubrum/database/errors/set_error.py
pyrubrum/handlers/__init__.py
pyrubrum/handlers/base_handler.py
pyrubrum/handlers/handler.py
pyrubrum/handlers/parameterized_base_handler.py
pyrubrum/handlers/parameterized_handler.py
pyrubrum/keyboard/__init__.py
pyrubrum/keyboard/button.py
pyrubrum/keyboard/element.py
pyrubrum/keyboard/keyboard.py
pyrubrum/menus/__init__.py
pyrubrum/menus/base_menu.py
pyrubrum/menus/deep_link_menu.py
pyrubrum/menus/link_menu.py
pyrubrum/menus/menu.py
pyrubrum/menus/page_menu.py
pyrubrum/menus/styles/__init__.py
pyrubrum/menus/styles/base_style.py
pyrubrum/menus/styles/menu_style.py
pyrubrum/menus/styles/page_style.py
pyrubrum/objects/__init__.py
pyrubrum/objects/user.py
pyrubrum/tree/__init__.py
pyrubrum/tree/node.py
pyrubrum/types/__init__.py
Pyrubrum-0.1a3.dist-info/LICENSE
Pyrubrum-0.1a3.dist-info/METADATA
Pyrubrum-0.1a3.dist-info/NOTICE
Pyrubrum-0.1a3.dist-info/WHEEL
Pyrubrum-0.1a3.dist-info/top_level.txt
Pyrubrum-0.1a3.dist-info/RECORD
